adversarialpytorchattacks/__init__.py
adversarialpytorchattacks/evaluate.py
adversarialpytorchattacks/utils.py
adversarialpytorchattacks/attacks/__init__.py
adversarialpytorchattacks/attacks/autoattack.py
adversarialpytorchattacks/attacks/cw.py
adversarialpytorchattacks/attacks/fgsm.py
adversarialpytorchattacks/attacks/mifgsm.py
adversarialpytorchattacks/attacks/pgd.py
adversarialtorchattacks-1.0.0.dist-info/METADATA
adversarialtorchattacks-1.0.0.dist-info/WHEEL
adversarialtorchattacks-1.0.0.dist-info/top_level.txt
adversarialtorchattacks-1.0.0.dist-info/RECORD
